simplejwt_session/__init__.py
simplejwt_session-0.0.5.dist-info/METADATA
simplejwt_session-0.0.5.dist-info/WHEEL
simplejwt_session-0.0.5.dist-info/top_level.txt
simplejwt_session-0.0.5.dist-info/RECORD
